<?xml version="1.0"?>
<vips><vip name="Drana"/><vip name="Lupaq"/><vip name="Super Girl"/><vip name="Blazer"/><vip name="Matroxxx"/><vip name="Mrs Tejmy"/><vip name="Lady bochi"/><vip name="Sosar"/><vip name="Girl hej"/><vip name="Gandor"/><vip name="Syntos"/><vip name="Jaffa"/><vip name="Xaur"/><vip name="The boy"/><vip name="Pandda men"/><vip name="Jesper"/><vip name="Pandda knight"/><vip name="Pontya of Pally"/><vip name="Pirre"/><vip name="Bubblan"/><vip name="Sawyer"/><vip name="Madona"/><vip name="Knaax"/></vips>
